Metadata-Version: 1.1
Name: ASINMatcher
Version: 1.0
Summary: A project to get the product details on Amazon
Home-page: UNKNOWN
Author: reetikaS
Author-email: UNKNOWN
License: UNKNOWN
Platform: UNKNOWN
Classifier: Programming Language :: Python :: 3
Classifier: License :: OSI Approved :: MIT License
